{
  "_class": "artboard",
  "backgroundColor": {
    "_class": "color",
    "alpha": 1,
    "blue": 0,
    "green": 0,
    "red": 0
  },
  "do_objectID": "1AD9969A-CC11-4992-A819-E078A4950CA9",
  "exportOptions": {
    "_class": "exportOptions",
    "exportFormats": [
      {
        "_class": "exportFormat",
        "absoluteSize": 0,
        "fileFormat": "png",
        "name": "",
        "namingScheme": 0,
        "scale": 2,
        "visibleScaleType": 0
      }
    ],
    "includedLayerIds": [
    ],
    "layerOptions": 0,
    "shouldTrim": false
  },
  "frame": {
    "_class": "rect",
    "constrainProportions": false,
    "height": 1920,
    "width": 1200,
    "x": -545,
    "y": -4001
  },
  "hasBackgroundColor": true,
  "hasClickThrough": false,
  "horizontalRulerData": {
    "_class": "rulerData",
    "base": 0,
    "guides": [
    ]
  },
  "includeBackgroundColorInExport": true,
  "includeInCloudUpload": true,
  "isFlippedHorizontal": false,
  "isFlippedVertical": false,
  "isLocked": false,
  "isVisible": true,
  "layerListExpandedType": 2,
  "layers": [
    {
      "class": "symbolInstance",
      "id": "D66B4E4A-1B5D-43EE-968C-9A3F8AE4A54A"
    },
    {
      "class": "group",
      "id": "0115D726-DBB9-4238-B1EE-EE0B9342477F"
    },
    {
      "class": "group",
      "id": "8AA2BE5B-EE43-45CF-A116-89F3016A9A4C"
    },
    {
      "class": "group",
      "id": "E4C15D9B-616D-464B-A42D-FB1DA1736ECC"
    },
    {
      "class": "group",
      "id": "63598BBD-2437-46FD-ACB0-8B96652958B8"
    },
    {
      "class": "group",
      "id": "B5143711-8F28-4A5F-94C4-3E3CE8A70EFD"
    },
    {
      "class": "group",
      "id": "5CB063A6-DA3B-4ACB-994E-E41288DF514C"
    },
    {
      "class": "group",
      "id": "0BF4EB40-5668-4208-AA9A-67A6F5DF548B"
    },
    {
      "class": "group",
      "id": "7DC3F5DE-F1B7-45D6-B43D-9B01B29087AA"
    },
    {
      "class": "group",
      "id": "7A6EA312-AF51-4AB6-9086-6925DD40EF35"
    },
    {
      "class": "group",
      "id": "05EDD437-A1EB-4A0C-8C3A-F4941D5705F6"
    },
    {
      "class": "text",
      "id": "289E46C4-A7E5-494F-8B15-6E9C86ADC706"
    },
    {
      "class": "symbolInstance",
      "id": "AFF6FF41-2CDA-4EFB-9A79-A8865F428CE0"
    },
    {
      "class": "group",
      "id": "4E615D47-071E-4176-88F7-9DC881DCE8BB"
    },
    {
      "class": "group",
      "id": "ECDA1DE9-070E-4801-ACE7-7E0C7A1A9A72"
    }
  ],
  "layout": {
    "_class": "layoutGrid",
    "columnWidth": 70,
    "drawHorizontal": true,
    "drawHorizontalLines": false,
    "drawVertical": true,
    "gutterHeight": 24,
    "gutterWidth": 24,
    "guttersOutside": false,
    "horizontalOffset": 48,
    "isEnabled": false,
    "numberOfColumns": 12,
    "rowHeightMultiplication": 1,
    "totalWidth": 1104
  },
  "name": "Main screen",
  "nameIsFixed": true,
  "resizesContent": false,
  "resizingConstraint": 63,
  "resizingType": 0,
  "rotation": 0,
  "shouldBreakMaskChain": false,
  "style": {
    "_class": "style",
    "endDecorationType": 0,
    "fills": [
      {
        "_class": "fill",
        "color": {
          "_class": "color",
          "alpha": 1,
          "blue": 1,
          "green": 1,
          "red": 1
        },
        "fillType": 0,
        "isEnabled": true,
        "noiseIndex": 0,
        "noiseIntensity": 0,
        "patternFillType": 1,
        "patternTileScale": 1
      }
    ],
    "miterLimit": 10,
    "startDecorationType": 0
  },
  "verticalRulerData": {
    "_class": "rulerData",
    "base": 0,
    "guides": [
    ]
  }
}