{
  "_class": "shapePath",
  "booleanOperation": -1,
  "do_objectID": "38E5F1F8-3EC9-492A-8044-61B236A9FC3C",
  "edited": true,
  "exportOptions": {
    "_class": "exportOptions",
    "exportFormats": [
    ],
    "includedLayerIds": [
    ],
    "layerOptions": 0,
    "shouldTrim": false
  },
  "frame": {
    "_class": "rect",
    "constrainProportions": false,
    "height": 240.8950243062959,
    "width": 198.9679190604282,
    "x": 0,
    "y": 0
  },
  "isFlippedHorizontal": false,
  "isFlippedVertical": false,
  "isLocked": false,
  "isVisible": true,
  "layerListExpandedType": 0,
  "name": "Path",
  "nameIsFixed": false,
  "path": {
    "_class": "path",
    "isClosed": false,
    "pointRadiusBehaviour": 0,
    "points": [
      {
        "_class": "curvePoint",
        "cornerRadius": 0,
        "curveFrom": "{1, 0.18543522673620763}",
        "curveMode": 4,
        "curveTo": "{1, 0.41417912094215659}",
        "hasCurveFrom": true,
        "hasCurveTo": false,
        "point": "{1, 0.41417912094215659}"
      },
      {
        "_class": "curvePoint",
        "cornerRadius": 0,
        "curveFrom": "{0.22386231069585091, 0}",
        "curveMode": 2,
        "curveTo": "{0.7761536699569056, 0}",
        "hasCurveFrom": true,
        "hasCurveTo": true,
        "point": "{0.50000266344212607, 0}"
      },
      {
        "_class": "curvePoint",
        "cornerRadius": 0,
        "curveFrom": "{0, 0.52835250563696612}",
        "curveMode": 3,
        "curveTo": "{-1.065376850431504e-05, 0.18543522673620763}",
        "hasCurveFrom": true,
        "hasCurveTo": true,
        "point": "{0, 0.41417912094215659}"
      },
      {
        "_class": "curvePoint",
        "cornerRadius": 0,
        "curveFrom": "{0.15365930313700216, 0.71299348274051422}",
        "curveMode": 3,
        "curveTo": "{0.055990880374160328, 0.63210798265005808}",
        "hasCurveFrom": true,
        "hasCurveTo": true,
        "point": "{0.14599924358243613, 0.70665272317311556}"
      },
      {
        "_class": "curvePoint",
        "cornerRadius": 0,
        "curveFrom": "{0.19758479068008339, 0.716704393524218}",
        "curveMode": 3,
        "curveTo": "{0.16378038321605315, 0.716704393524218}",
        "hasCurveFrom": true,
        "hasCurveTo": true,
        "point": "{0.17516926174711156, 0.716704393524218}"
      },
      {
        "_class": "curvePoint",
        "cornerRadius": 0,
        "curveFrom": "{0.21578675416961873, 0.6736207634503969}",
        "curveMode": 2,
        "curveTo": "{0.21578675416961873, 0.7016224754996051}",
        "hasCurveFrom": true,
        "hasCurveTo": true,
        "point": "{0.21578675416961873, 0.6830546840872086}"
      },
      {
        "_class": "curvePoint",
        "cornerRadius": 0,
        "curveFrom": "{0.12814885445354152, 0.59645941163752214}",
        "curveMode": 3,
        "curveTo": "{0.21090732819466559, 0.66498991744216318}",
        "hasCurveFrom": true,
        "hasCurveTo": true,
        "point": "{0.20333249878813378, 0.65871975784211201}"
      },
      {
        "_class": "curvePoint",
        "cornerRadius": 0,
        "curveFrom": "{0.081256292382022782, 0.22291498440181973}",
        "curveMode": 3,
        "curveTo": "{0.081256292382022782, 0.50960380180824172}",
        "hasCurveFrom": true,
        "hasCurveTo": true,
        "point": "{0.081256292382022782, 0.41417912094215659}"
      },
      {
        "_class": "curvePoint",
        "cornerRadius": 0,
        "curveFrom": "{0.73089646135079134, 0.06731706886585577}",
        "curveMode": 4,
        "curveTo": "{0.26910886553346086, 0.067312656367896406}",
        "hasCurveFrom": true,
        "hasCurveTo": true,
        "point": "{0.50000266344212607, 0.067312656367896406}"
      },
      {
        "_class": "curvePoint",
        "cornerRadius": 0,
        "curveFrom": "{0.91874370761797719, 0.50981560171028428}",
        "curveMode": 3,
        "curveTo": "{0.91874370761797719, 0.22291939689977897}",
        "hasCurveFrom": true,
        "hasCurveTo": true,
        "point": "{0.91874370761797719, 0.41417912094215659}"
      },
      {
        "_class": "curvePoint",
        "cornerRadius": 0,
        "curveFrom": "{0.79590575676381137, 0.65935515754823959}",
        "curveMode": 4,
        "curveTo": "{0.8717659153984243, 0.59654766159670647}",
        "hasCurveFrom": false,
        "hasCurveTo": true,
        "point": "{0.79590575676381137, 0.65935515754823959}"
      },
      {
        "_class": "curvePoint",
        "cornerRadius": 0,
        "curveFrom": "{0.79591641053231543, 0.65936398254415807}",
        "curveMode": 1,
        "curveTo": "{0.79591641053231543, 0.65936398254415807}",
        "hasCurveFrom": false,
        "hasCurveTo": false,
        "point": "{0.79591641053231543, 0.65936398254415807}"
      },
      {
        "_class": "curvePoint",
        "cornerRadius": 0,
        "curveFrom": "{0.44228054568602282, 0.95228765956695749}",
        "curveMode": 1,
        "curveTo": "{0.44228054568602282, 0.95228765956695749}",
        "hasCurveFrom": false,
        "hasCurveTo": false,
        "point": "{0.44228054568602282, 0.95228765956695749}"
      },
      {
        "_class": "curvePoint",
        "cornerRadius": 0,
        "curveFrom": "{0.49989079887283128, 1}",
        "curveMode": 1,
        "curveTo": "{0.49989079887283128, 1}",
        "hasCurveFrom": false,
        "hasCurveTo": false,
        "point": "{0.49989079887283128, 1}"
      },
      {
        "_class": "curvePoint",
        "cornerRadius": 0,
        "curveFrom": "{0.85378768104747849, 0.70688217306699497}",
        "curveMode": 1,
        "curveTo": "{0.85378768104747849, 0.70688217306699497}",
        "hasCurveFrom": false,
        "hasCurveTo": false,
        "point": "{0.85378768104747849, 0.70688217306699497}"
      },
      {
        "_class": "curvePoint",
        "cornerRadius": 0,
        "curveFrom": "{0.94412631107938649, 0.63192265773577083}",
        "curveMode": 4,
        "curveTo": "{0.85376637351047002, 0.70686893557311725}",
        "hasCurveFrom": true,
        "hasCurveTo": false,
        "point": "{0.85376637351047002, 0.70686893557311725}"
      },
      {
        "_class": "curvePoint",
        "cornerRadius": 0,
        "curveFrom": "{1, 0.41417912094215659}",
        "curveMode": 4,
        "curveTo": "{1, 0.52845399309002816}",
        "hasCurveFrom": false,
        "hasCurveTo": true,
        "point": "{1, 0.41417912094215659}"
      }
    ]
  },
  "resizingConstraint": 63,
  "resizingType": 0,
  "rotation": 0,
  "shouldBreakMaskChain": false
}