{
  "_class": "symbolInstance",
  "do_objectID": "321F3FB0-0393-45FF-BF22-B6FB6AFF05AE",
  "exportOptions": {
    "_class": "exportOptions",
    "exportFormats": [
    ],
    "includedLayerIds": [
    ],
    "layerOptions": 0,
    "shouldTrim": false
  },
  "frame": {
    "_class": "rect",
    "constrainProportions": false,
    "height": 64,
    "width": 336,
    "x": 384,
    "y": 1663
  },
  "horizontalSpacing": 0,
  "isFlippedHorizontal": false,
  "isFlippedVertical": false,
  "isLocked": false,
  "isVisible": true,
  "layerListExpandedType": 0,
  "masterInfluenceEdgeMaxXPadding": 0,
  "masterInfluenceEdgeMaxYPadding": 0,
  "masterInfluenceEdgeMinXPadding": 0,
  "masterInfluenceEdgeMinYPadding": 0,
  "name": "button/route/right",
  "nameIsFixed": false,
  "overrides": {
    "2D6B3FFE-43E9-4C61-96C3-B28C2C323C53": {
      "symbolID": "B82EA5F3-7BF3-4AFA-A9B2-494CF8E747A4"
    }
  },
  "resizingConstraint": 63,
  "resizingType": 0,
  "rotation": 0,
  "shouldBreakMaskChain": false,
  "style": {
    "_class": "style",
    "endDecorationType": 0,
    "miterLimit": 10,
    "startDecorationType": 0
  },
  "symbolID": "7DFEDA59-D833-4D8B-B498-733707F7591D",
  "verticalSpacing": 0
}